<?xml version="1.0" ?>
<annotation>
	<folder>imgs/</folder>
	<filename>VOC2007_1.jpg</filename>
	<path>VOC2007_1.jpg</path>
	<size>
		<width>500</width>
		<height>336</height>
		<depth>3</depth>
	</size>
	<segmented>0</segmented>
	<object>
		<name>hand</name>
		<pose>Unspecified</pose>
		<truncated>0</truncated>
		<difficult>0</difficult>
		<bndbox>
			<xmin>110</xmin>
			<ymin>223</ymin>
			<xmax>133</xmax>
			<ymax>247</ymax>
		</bndbox>
	</object>
	<object>
		<name>hand</name>
		<pose>Unspecified</pose>
		<truncated>0</truncated>
		<difficult>0</difficult>
		<bndbox>
			<xmin>106</xmin>
			<ymin>243</ymin>
			<xmax>130</xmax>
			<ymax>270</ymax>
		</bndbox>
	</object>
</annotation>
