<?xml version="1.0" ?>
<annotation>
	<folder>imgs/</folder>
	<filename>VOC2010_234.jpg</filename>
	<path>VOC2010_234.jpg</path>
	<size>
		<width>500</width>
		<height>333</height>
		<depth>3</depth>
	</size>
	<segmented>0</segmented>
	<object>
		<name>hand</name>
		<pose>Unspecified</pose>
		<truncated>0</truncated>
		<difficult>0</difficult>
		<bndbox>
			<xmin>86</xmin>
			<ymin>384</ymin>
			<xmax>163</xmax>
			<ymax>469</ymax>
		</bndbox>
	</object>
	<object>
		<name>hand</name>
		<pose>Unspecified</pose>
		<truncated>0</truncated>
		<difficult>0</difficult>
		<bndbox>
			<xmin>168</xmin>
			<ymin>429</ymin>
			<xmax>217</xmax>
			<ymax>478</ymax>
		</bndbox>
	</object>
	<object>
		<name>hand</name>
		<pose>Unspecified</pose>
		<truncated>0</truncated>
		<difficult>0</difficult>
		<bndbox>
			<xmin>29</xmin>
			<ymin>435</ymin>
			<xmax>84</xmax>
			<ymax>491</ymax>
		</bndbox>
	</object>
</annotation>
