<?xml version="1.0" ?>
<annotation>
	<folder>imgs/</folder>
	<filename>VOC2010_1407.jpg</filename>
	<path>VOC2010_1407.jpg</path>
	<size>
		<width>281</width>
		<height>500</height>
		<depth>3</depth>
	</size>
	<segmented>0</segmented>
	<object>
		<name>hand</name>
		<pose>Unspecified</pose>
		<truncated>0</truncated>
		<difficult>0</difficult>
		<bndbox>
			<xmin>278</xmin>
			<ymin>67</ymin>
			<xmax>312</xmax>
			<ymax>102</ymax>
		</bndbox>
	</object>
	<object>
		<name>hand</name>
		<pose>Unspecified</pose>
		<truncated>0</truncated>
		<difficult>0</difficult>
		<bndbox>
			<xmin>215</xmin>
			<ymin>138</ymin>
			<xmax>246</xmax>
			<ymax>169</ymax>
		</bndbox>
	</object>
</annotation>
